Project/__init__.py
Project/functions.py
Project/test2.py
ProjectPyAfaf-0.0.1.dist-info/LICENCE.txt
ProjectPyAfaf-0.0.1.dist-info/METADATA
ProjectPyAfaf-0.0.1.dist-info/WHEEL
ProjectPyAfaf-0.0.1.dist-info/top_level.txt
ProjectPyAfaf-0.0.1.dist-info/RECORD
